{
  "id": "娑",
  "kanjialiveData": null,
  "jishoData": {
    "query": "娑",
    "found": true,
    "strokeCount": 10,
    "meaning": "old woman",
    "kunyomi": [],
    "onyomi": [
      "シャ",
      "サ"
    ],
    "onyomiExamples": [
      {
        "example": "娑婆",
        "reading": "シャバ",
        "meaning": {
          "vi": "this world, this life, the free world (outside of prison, the army, red light district, etc.), this corrupt world, present world"
        },
        "romaji": "shaba"
      },
      {
        "example": "娑婆気",
        "reading": "シャバケ",
        "meaning": {
          "en": "worldly desires or ambitions"
        },
        "romaji": "shabake"
      },
      {
        "example": "沙羅",
        "reading": "シャラ",
        "meaning": {
          "vi": "sal (tree) (Shorea robusta), saul, Japanese stewartia (Stewartia pseudocamellia)"
        },
        "romaji": "shara"
      },
      {
        "example": "娑羅樹",
        "reading": "サラジュ",
        "meaning": {
          "vi": "Japanese stewartia (Stewartia pseudocamellia), sal (tree) (Shorea robusta), saul"
        },
        "romaji": "saraju"
      }
    ],
    "kunyomiExamples": [],
    "radical": {
      "symbol": "女",
      "meaning": "woman, female"
    },
    "parts": [
      "ノ",
      "女",
      "小",
      "汁"
    ],
    "strokeOrderDiagramUri": "http://classic.jisho.org/static/images/stroke_diagrams/23057_frames.png",
    "strokeOrderSvgUri": "https://d1w6u4xc3l95km.cloudfront.net/kanji-2015-03/05a11.svg",
    "strokeOrderGifUri": "https://raw.githubusercontent.com/mistval/kanji_images/master/gifs/5a11.gif",
    "uri": "https://jisho.org/search/%E5%A8%91%23kanji"
  },
  "hanViet": [
    "sa"
  ]
}