{
  "id": "屍",
  "kanjialiveData": null,
  "jishoData": {
    "query": "屍",
    "found": true,
    "strokeCount": 9,
    "meaning": "corpse",
    "kunyomi": [
      "しかばね"
    ],
    "onyomi": [
      "シ"
    ],
    "onyomiExamples": [
      {
        "example": "屍",
        "reading": "シカバネ",
        "meaning": {
          "vi": "corpse, kanji \"corpse\" radical"
        },
        "romaji": "shikabane"
      },
      {
        "example": "死体",
        "reading": "シタイ",
        "meaning": {
          "vi": "dead body, corpse, cadaver, carcass"
        },
        "romaji": "shitai"
      },
      {
        "example": "死屍",
        "reading": "シシ",
        "meaning": {
          "vi": "corpse"
        },
        "romaji": "shishi"
      },
      {
        "example": "検死",
        "reading": "ケンシ",
        "meaning": {
          "vi": "autopsy, post-mortem (examination), (coroner's) inquest, examination of a body to determine if a crime has been committed"
        },
        "romaji": "kenshi"
      }
    ],
    "kunyomiExamples": [
      {
        "example": "屍",
        "reading": "しかばね",
        "meaning": {
          "vi": "corpse, kanji \"corpse\" radical"
        },
        "romaji": "shikabane"
      },
      {
        "example": "屍をさらす",
        "reading": "しかばねをさらす",
        "meaning": {
          "en": "to die on the battlefield"
        },
        "romaji": "shikabanewosarasu"
      },
      {
        "example": "生ける屍",
        "reading": "いけるしかばね",
        "meaning": {
          "vi": "living corpse"
        },
        "romaji": "ikerushikabane"
      }
    ],
    "radical": {
      "symbol": "尸",
      "meaning": "corpse"
    },
    "parts": [
      "一",
      "匕",
      "夕",
      "尸",
      "歹"
    ],
    "strokeOrderDiagramUri": "http://classic.jisho.org/static/images/stroke_diagrams/23629_frames.png",
    "strokeOrderSvgUri": "https://d1w6u4xc3l95km.cloudfront.net/kanji-2015-03/05c4d.svg",
    "strokeOrderGifUri": "https://raw.githubusercontent.com/mistval/kanji_images/master/gifs/5c4d.gif",
    "uri": "https://jisho.org/search/%E5%B1%8D%23kanji"
  },
  "hanViet": [
    "thi"
  ]
}