{
  "id": "腿",
  "kanjialiveData": null,
  "jishoData": {
    "query": "腿",
    "found": true,
    "strokeCount": 13,
    "meaning": "thigh, femur",
    "kunyomi": [
      "もも"
    ],
    "onyomi": [
      "タイ"
    ],
    "onyomiExamples": [
      {
        "example": "腿口類",
        "reading": "タイコウルイ",
        "meaning": {
          "vi": "Merostomata (group comprising the sea scorpions and the horseshoe crabs)"
        },
        "romaji": "taikourui"
      },
      {
        "example": "腿骨",
        "reading": "タイコツ",
        "meaning": {
          "vi": "bones of the upper and lower leg"
        },
        "romaji": "taikotsu"
      },
      {
        "example": "大腿",
        "reading": "ダイタイ",
        "meaning": {
          "en": "thigh"
        },
        "romaji": "daitai"
      },
      {
        "example": "上腿",
        "reading": "ジョウタイ",
        "meaning": {
          "en": "thigh"
        },
        "romaji": "joutai"
      }
    ],
    "kunyomiExamples": [
      {
        "example": "腿",
        "reading": "もも",
        "meaning": {
          "en": "thigh"
        },
        "romaji": "momo"
      },
      {
        "example": "腿赤ノスリ",
        "reading": "ももあかノスリ",
        "meaning": {
          "vi": "Harris's hawk (Parabuteo unicinctus), Harris hawk"
        },
        "romaji": "momoakanosuri"
      },
      {
        "example": "太もも",
        "reading": "ふともも",
        "meaning": {
          "en": "thigh, buttocks, arse, ass, butt"
        },
        "romaji": "futomomo"
      },
      {
        "example": "外股",
        "reading": "そともも",
        "meaning": {
          "en": "outer thigh"
        },
        "romaji": "sotomomo"
      }
    ],
    "radical": {
      "symbol": "肉",
      "forms": [
        "⺼"
      ],
      "meaning": "meat"
    },
    "parts": [
      "月",
      "艮",
      "込"
    ],
    "strokeOrderDiagramUri": "http://classic.jisho.org/static/images/stroke_diagrams/33151_frames.png",
    "strokeOrderSvgUri": "https://d1w6u4xc3l95km.cloudfront.net/kanji-2015-03/0817f.svg",
    "strokeOrderGifUri": "https://raw.githubusercontent.com/mistval/kanji_images/master/gifs/817f.gif",
    "uri": "https://jisho.org/search/%E8%85%BF%23kanji"
  },
  "hanViet": [
    "thoái",
    "thối"
  ]
}