{
  "id": "辟",
  "kanjialiveData": null,
  "jishoData": {
    "query": "辟",
    "found": true,
    "strokeCount": 13,
    "meaning": "false, punish, crime, law",
    "kunyomi": [
      "きみ",
      "ひら.く",
      "め.す"
    ],
    "onyomi": [
      "ヘキ",
      "ヒ"
    ],
    "onyomiExamples": [
      {
        "example": "辟",
        "reading": "ヘキ",
        "meaning": {
          "vi": "false, punish, crime, law, ruler"
        },
        "romaji": "heki"
      },
      {
        "example": "辟易",
        "reading": "ヘキエキ",
        "meaning": {
          "vi": "to be fed up (with), to be tired (of), to be bored (with), to be unable to bear, to be stumped, to be nonplussed, to be disconcerted, to wince, to shrink back, to cringe"
        },
        "romaji": "hekieki"
      },
      {
        "example": "大辟",
        "reading": "タイヘキ",
        "meaning": {
          "vi": "severe punishment, death penalty"
        },
        "romaji": "taiheki"
      },
      {
        "example": "復辟",
        "reading": "フクヘキ",
        "meaning": {
          "en": "restoration (of an abdicated ruler)"
        },
        "romaji": "fukuheki"
      }
    ],
    "kunyomiExamples": [],
    "radical": {
      "symbol": "辛",
      "meaning": "bitter"
    },
    "parts": [
      "十",
      "口",
      "尸",
      "立",
      "辛"
    ],
    "strokeOrderDiagramUri": "http://classic.jisho.org/static/images/stroke_diagrams/36767_frames.png",
    "strokeOrderSvgUri": "https://d1w6u4xc3l95km.cloudfront.net/kanji-2015-03/08f9f.svg",
    "strokeOrderGifUri": "https://raw.githubusercontent.com/mistval/kanji_images/master/gifs/8f9f.gif",
    "uri": "https://jisho.org/search/%E8%BE%9F%23kanji"
  },
  "hanViet": [
    "bách",
    "bễ",
    "phích",
    "thí",
    "tích",
    "tịch",
    "tỵ"
  ]
}